pure_protobuf/__init__.py
pure_protobuf/dataclasses_.py
pure_protobuf/enums.py
pure_protobuf/fields.py
pure_protobuf/io_.py
pure_protobuf/oneof.py
pure_protobuf/serializers/__init__.py
pure_protobuf/serializers/google.py
pure_protobuf/types/__init__.py
pure_protobuf/types/google.py
hidden_pure_protobuf-0.2.dist-info/LICENSE
hidden_pure_protobuf-0.2.dist-info/METADATA
hidden_pure_protobuf-0.2.dist-info/WHEEL
hidden_pure_protobuf-0.2.dist-info/top_level.txt
hidden_pure_protobuf-0.2.dist-info/zip-safe
hidden_pure_protobuf-0.2.dist-info/RECORD
